[{"id":"7994","districtId":"1135","name":"Bendotretek"},{"id":"8264","districtId":"1135","name":"Bulang"},{"id":"8406","districtId":"1135","name":"Cangkringturi"},{"id":"8777","districtId":"1135","name":"Gampang"},{"id":"8857","districtId":"1135","name":"Gedangrowo"},{"id":"11216","districtId":"1135","name":"Simogirang"},{"id":"11226","districtId":"1135","name":"Simpang"},{"id":"11519","districtId":"1135","name":"Jatialun-Alun"},{"id":"11535","districtId":"1135","name":"Jatikalang"},{"id":"11593","districtId":"1135","name":"Jedongcangkring"},{"id":"11776","districtId":"1135","name":"Kajartengguli"},{"id":"12383","districtId":"1135","name":"Kedungkembar"},{"id":"12444","districtId":"1135","name":"Kedungsugo"},{"id":"12459","districtId":"1135","name":"Kedungwonokerto"},{"id":"14317","districtId":"1135","name":"Pejangkungan"},{"id":"14628","districtId":"1135","name":"Prambon"},{"id":"18082","districtId":"1135","name":"Temu"},{"id":"18421","districtId":"1135","name":"Watutulis"},{"id":"18466","districtId":"1135","name":"Wirobiting"},{"id":"18530","districtId":"1135","name":"Wonoplintahan"}]