[{"id":"8126","districtId":"1170","name":"Blumbungan"},{"id":"8656","districtId":"1170","name":"Duko Timur"},{"id":"9073","districtId":"1170","name":"Grujugan"},{"id":"11769","districtId":"1170","name":"Kaduara Barat"},{"id":"13018","districtId":"1170","name":"Lancar"},{"id":"13035","districtId":"1170","name":"Larangan Dalam"},{"id":"13036","districtId":"1170","name":"Larangan Luar"},{"id":"13535","districtId":"1170","name":"Montok"},{"id":"14092","districtId":"1170","name":"Panaguan"},{"id":"14353","districtId":"1170","name":"Peltong"},{"id":"17950","districtId":"1170","name":"Taraban"},{"id":"18105","districtId":"1170","name":"Tentenan Barat"},{"id":"18106","districtId":"1170","name":"Tentenan Timur"},{"id":"18214","districtId":"1170","name":"Trasak"}]