[{"id":"8194","districtId":"1186","name":"Brangkal"},{"id":"8436","districtId":"1186","name":"Cengkong"},{"id":"8519","districtId":"1186","name":"Dagangan"},{"id":"10913","districtId":"1186","name":"Selogabus"},{"id":"10971","districtId":"1186","name":"Sembung"},{"id":"11015","districtId":"1186","name":"Sendangrejo"},{"id":"12522","districtId":"1186","name":"Kemlaten"},{"id":"12937","districtId":"1186","name":"Kumpulrejo"},{"id":"13285","districtId":"1186","name":"Margorejo"},{"id":"13384","districtId":"1186","name":"Mergoasri"},{"id":"13475","districtId":"1186","name":"Mojomalang"},{"id":"13711","districtId":"1186","name":"Ngawun"},{"id":"13941","districtId":"1186","name":"Pacing"},{"id":"14213","districtId":"1186","name":"Parangbatu"},{"id":"17235","districtId":"1186","name":"Suciharjo"},{"id":"17262","districtId":"1186","name":"Sugihwaras"},{"id":"17357","districtId":"1186","name":"Sukorejo"},{"id":"18606","districtId":"1186","name":"Wukirharjo"}]