[{"id":"8766","districtId":"1289","name":"Gambiran"},{"id":"9034","districtId":"1289","name":"Gondanggunung"},{"id":"10870","districtId":"1289","name":"Segawe"},{"id":"11141","districtId":"1289","name":"Sidomulyo"},{"id":"12357","districtId":"1289","name":"Kedungcangkring"},{"id":"12849","districtId":"1289","name":"Kradinan"},{"id":"13579","districtId":"1289","name":"Mulyosari"},{"id":"13989","districtId":"1289","name":"Pagerwojo"},{"id":"14391","districtId":"1289","name":"Penjor"},{"id":"14977","districtId":"1289","name":"Samar"},{"id":"18533","districtId":"1289","name":"Wonorejo"}]