[{"id":"10502","districtId":"1341","name":"Mergasana"},{"id":"10515","districtId":"1341","name":"Kertanegara"},{"id":"10525","districtId":"1341","name":"Karangtengah"},{"id":"10528","districtId":"1341","name":"Kasih"},{"id":"10533","districtId":"1341","name":"Condong"},{"id":"10543","districtId":"1341","name":"Karangpucung"},{"id":"10560","districtId":"1341","name":"Karangasem"},{"id":"10565","districtId":"1341","name":"Adiarsa"},{"id":"10581","districtId":"1341","name":"Langkap"},{"id":"10583","districtId":"1341","name":"Darma"},{"id":"10585","districtId":"1341","name":"Krangean"}]