[{"id":"15420","districtId":"1448","name":"Arjosari"},{"id":"15423","districtId":"1448","name":"Balearjosari"},{"id":"15427","districtId":"1448","name":"Blimbing"},{"id":"15429","districtId":"1448","name":"Bunulrejo"},{"id":"15437","districtId":"1448","name":"Jodipan"},{"id":"15443","districtId":"1448","name":"Kesatrian"},{"id":"15456","districtId":"1448","name":"Pandanwangi"},{"id":"15459","districtId":"1448","name":"Polehan"},{"id":"15460","districtId":"1448","name":"Polowijen"},{"id":"15461","districtId":"1448","name":"Purwantoro"},{"id":"15462","districtId":"1448","name":"Purwodadi"}]