[{"id":"15535","districtId":"1491","name":"Bangsri"},{"id":"15693","districtId":"1491","name":"Dayu"},{"id":"15713","districtId":"1491","name":"Doplang"},{"id":"15797","districtId":"1491","name":"Gerdu"},{"id":"15839","districtId":"1491","name":"Gondangmanis"},{"id":"15877","districtId":"1491","name":"Harjosari"},{"id":"16045","districtId":"1491","name":"Karang"},{"id":"16079","districtId":"1491","name":"Karangpandan"},{"id":"16393","districtId":"1491","name":"Ngemplak"},{"id":"16611","districtId":"1491","name":"Salam"},{"id":"16911","districtId":"1491","name":"Tohkuning"}]