[{"id":"15627","districtId":"1528","name":"Bubakan"},{"id":"15707","districtId":"1528","name":"Doho"},{"id":"15772","districtId":"1528","name":"Gemawang"},{"id":"15812","districtId":"1528","name":"Girimarto"},{"id":"15820","districtId":"1528","name":"Giriwarno"},{"id":"15924","districtId":"1528","name":"Jatirejo"},{"id":"15950","districtId":"1528","name":"Jendi"},{"id":"16437","districtId":"1528","name":"Nungkulan"},{"id":"16636","districtId":"1528","name":"Sanan"},{"id":"16665","districtId":"1528","name":"Selorejo"},{"id":"16667","districtId":"1528","name":"Semagar"},{"id":"16712","districtId":"1528","name":"Sidokarto"},{"id":"16819","districtId":"1528","name":"Tambakmerang"},{"id":"16948","districtId":"1528","name":"Waleng"}]