[{"id":"15674","districtId":"1544","name":"Cerme"},{"id":"15959","districtId":"1544","name":"Jerukan"},{"id":"15998","districtId":"1544","name":"Juwangi"},{"id":"16026","districtId":"1544","name":"Kalimati"},{"id":"16111","districtId":"1544","name":"Kayen"},{"id":"16224","districtId":"1544","name":"Krobokan"},{"id":"16374","districtId":"1544","name":"Ngaren"},{"id":"16408","districtId":"1544","name":"Ngleses"},{"id":"16503","districtId":"1544","name":"Pilangrejo"},{"id":"16613","districtId":"1544","name":"Sambeng"}]