[{"id":"15870","districtId":"1562","name":"Guworejo"},{"id":"15996","districtId":"1562","name":"Jurangjero"},{"id":"16144","districtId":"1562","name":"Kedungwaduk"},{"id":"16228","districtId":"1562","name":"Kroyo"},{"id":"16331","districtId":"1562","name":"Mojorejo"},{"id":"16481","districtId":"1562","name":"Pelemgadung"},{"id":"16513","districtId":"1562","name":"Plosokerep"},{"id":"16527","districtId":"1562","name":"Plumbungan"},{"id":"16579","districtId":"1562","name":"Puro"},{"id":"16643","districtId":"1562","name":"Saradan"}]