[{"id":"18646","districtId":"1589","name":"Jabon"},{"id":"18647","districtId":"1589","name":"Plandi"},{"id":"18648","districtId":"1589","name":"Kaliwungu"},{"id":"18649","districtId":"1589","name":"Jombatan"},{"id":"18650","districtId":"1589","name":"Jelakombo"},{"id":"18651","districtId":"1589","name":"Tunggorono"},{"id":"18652","districtId":"1589","name":"Kepanjen"},{"id":"18654","districtId":"1589","name":"Pulolor"},{"id":"18656","districtId":"1589","name":"Jombang"},{"id":"18657","districtId":"1589","name":"Candimulyo"},{"id":"18658","districtId":"1589","name":"Mojongapit"},{"id":"18661","districtId":"1589","name":"Denanyar"},{"id":"18662","districtId":"1589","name":"Sambongdukuh"},{"id":"18663","districtId":"1589","name":"Tambakrejo"},{"id":"18664","districtId":"1589","name":"Dapurkejambon"},{"id":"18666","districtId":"1589","name":"Sumberjo"},{"id":"18667","districtId":"1589","name":"Plosogeneng"},{"id":"18668","districtId":"1589","name":"Banjardowo"},{"id":"18693","districtId":"1589","name":"Sengon"},{"id":"18694","districtId":"1589","name":"Kepatihan"}]