[{"id":"20019","districtId":"1996","name":"Kandis I"},{"id":"20020","districtId":"1996","name":"Kandis Ii"},{"id":"20285","districtId":"1996","name":"Kumbang Ilir"},{"id":"20287","districtId":"1996","name":"Kumbang Ulu"},{"id":"20430","districtId":"1996","name":"Lubuk Rukam"},{"id":"20438","districtId":"1996","name":"Lubuk Segonang"},{"id":"20603","districtId":"1996","name":"Miji"},{"id":"20655","districtId":"1996","name":"Muara Kumbang"},{"id":"20892","districtId":"1996","name":"Pandan Arang"},{"id":"21271","districtId":"1996","name":"Santapan Barat"},{"id":"21272","districtId":"1996","name":"Santapan Timur"},{"id":"21952","districtId":"1996","name":"Tanjung Alai"}]