[{"id":"23105","districtId":"2089","name":"Bukit Makmur"},{"id":"23117","districtId":"2089","name":"Bumi Mulya"},{"id":"23476","districtId":"2089","name":"Lubuk Mukti"},{"id":"23507","districtId":"2089","name":"Maju Makmur"},{"id":"23524","districtId":"2089","name":"Marga Mukti"},{"id":"23526","districtId":"2089","name":"Marga Mulya Sakti"},{"id":"23538","districtId":"2089","name":"Mekar Mulya"},{"id":"23765","districtId":"2089","name":"Penarik"},{"id":"23909","districtId":"2089","name":"Sendang Mulyo"},{"id":"23924","districtId":"2089","name":"Sido Dadi"},{"id":"23933","districtId":"2089","name":"Sido Mulyo"},{"id":"23984","districtId":"2089","name":"Suka Maju"},{"id":"24041","districtId":"2089","name":"Sumber Mulya"},{"id":"24379","districtId":"2089","name":"Wonosobo"}]