[{"id":"23152","districtId":"2111","name":"Darat Sawah"},{"id":"23667","districtId":"2111","name":"Pagar Dewa"},{"id":"23764","districtId":"2111","name":"Penantian"},{"id":"23854","districtId":"2111","name":"Rigangan I"},{"id":"23855","districtId":"2111","name":"Rigangan Ii"},{"id":"23856","districtId":"2111","name":"Rigangan Iii"},{"id":"23963","districtId":"2111","name":"Siring Agung"},{"id":"24005","districtId":"2111","name":"Suka Rami Ii"},{"id":"24019","districtId":"2111","name":"Sukarami"},{"id":"24152","districtId":"2111","name":"Talang Marap"},{"id":"24178","districtId":"2111","name":"Talang Tais"},{"id":"24246","districtId":"2111","name":"Tanjung Ganti I"},{"id":"24247","districtId":"2111","name":"Tanjung Ganti Ii"}]