[{"id":"24732","districtId":"2224","name":"Bayah Barat"},{"id":"27987","districtId":"2224","name":"Pasirgombong"},{"id":"28002","districtId":"2224","name":"Cisuren"},{"id":"31337","districtId":"2224","name":"Bayah Timur"},{"id":"31344","districtId":"2224","name":"Cimancak"},{"id":"31345","districtId":"2224","name":"Suwakan"},{"id":"31348","districtId":"2224","name":"Cidikit"},{"id":"70471","districtId":"2224","name":"Sawarna Timur"},{"id":"70474","districtId":"2224","name":"Sawarna"},{"id":"70477","districtId":"2224","name":"Darmasari"},{"id":"70968","districtId":"2224","name":"Pamubulan"}]