[{"id":"24870","districtId":"2270","name":"Jotang"},{"id":"24883","districtId":"2270","name":"Ketapang"},{"id":"24904","districtId":"2270","name":"Sijeruk"},{"id":"24914","districtId":"2270","name":"Trompo"},{"id":"24916","districtId":"2270","name":"Tunggulrejo"},{"id":"31516","districtId":"2270","name":"Banyutowo"},{"id":"31542","districtId":"2270","name":"Jetis"},{"id":"31546","districtId":"2270","name":"Kalibutuwetan"},{"id":"31559","districtId":"2270","name":"Karangsari"},{"id":"31561","districtId":"2270","name":"Kebondalem"},{"id":"31575","districtId":"2270","name":"Langenharjo"},{"id":"31589","districtId":"2270","name":"Pegulon"},{"id":"33361","districtId":"2270","name":"Balok"},{"id":"33364","districtId":"2270","name":"Bandengan"},{"id":"33394","districtId":"2270","name":"Bugangin"},{"id":"33577","districtId":"2270","name":"Ngilir"},{"id":"33594","districtId":"2270","name":"Patukangan"},{"id":"33600","districtId":"2270","name":"Pekauman"},{"id":"70660","districtId":"2270","name":"Candiroto"},{"id":"70750","districtId":"2270","name":"Sukodono"}]