[{"id":"24911","districtId":"2278","name":"Tegalglagah"},{"id":"31528","districtId":"2278","name":"Cipelem"},{"id":"31543","districtId":"2278","name":"Jubang"},{"id":"31572","districtId":"2278","name":"Kluwut"},{"id":"31594","districtId":"2278","name":"Petunjungan"},{"id":"33366","districtId":"2278","name":"Bangsri"},{"id":"33372","districtId":"2278","name":"Banjaratma"},{"id":"33398","districtId":"2278","name":"Bulakamba"},{"id":"33399","districtId":"2278","name":"Bulakparen"},{"id":"33401","districtId":"2278","name":"Bulusari"},{"id":"33407","districtId":"2278","name":"Cimohong"},{"id":"33425","districtId":"2278","name":"Dukuhlo"},{"id":"33435","districtId":"2278","name":"Grinting"},{"id":"33482","districtId":"2278","name":"Karangsari"},{"id":"33550","districtId":"2278","name":"Luwungragi"},{"id":"33586","districtId":"2278","name":"Pakijangan"},{"id":"33626","districtId":"2278","name":"Pulogading"},{"id":"33630","districtId":"2278","name":"Rancawuluh"},{"id":"33664","districtId":"2278","name":"Siwuluh"}]