[{"id":"26848","districtId":"2404","name":"Muara"},{"id":"27007","districtId":"2404","name":"Purwawinangun"},{"id":"27176","districtId":"2404","name":"Surakarta"},{"id":"27177","districtId":"2404","name":"Suranenggala"},{"id":"27178","districtId":"2404","name":"Suranenggala Kidul"},{"id":"27179","districtId":"2404","name":"Suranenggala Kulon"},{"id":"27180","districtId":"2404","name":"Suranenggala Lor"},{"id":"30882","districtId":"2404","name":"Karangreja"},{"id":"30951","districtId":"2404","name":"Keraton"}]