[{"id":"28329","districtId":"2553","name":"Banyuasih"},{"id":"28482","districtId":"2553","name":"Cicinde Selatan"},{"id":"28483","districtId":"2553","name":"Cicinde Utara"},{"id":"28728","districtId":"2553","name":"Gembongan"},{"id":"28729","districtId":"2553","name":"Gempol"},{"id":"28730","districtId":"2553","name":"Gempol Kolot"},{"id":"28796","districtId":"2553","name":"Jayamukti"},{"id":"28890","districtId":"2553","name":"Kertaraharja"},{"id":"29000","districtId":"2553","name":"Mekarasih"},{"id":"29095","districtId":"2553","name":"Pamekaran"},{"id":"29429","districtId":"2553","name":"Talunjaya"},{"id":"29444","districtId":"2553","name":"Tanjung"}]