[{"id":"31062","districtId":"2794","name":"Sambiroto"},{"id":"31099","districtId":"2794","name":"Sendangrejo"},{"id":"31230","districtId":"2794","name":"Tayu Kulon"},{"id":"31231","districtId":"2794","name":"Tayu Wetan"},{"id":"31245","districtId":"2794","name":"Tendas"},{"id":"31292","districtId":"2794","name":"Tunggulsari"},{"id":"34142","districtId":"2794","name":"Bendokaton Kidul"},{"id":"34179","districtId":"2794","name":"Bulungan"},{"id":"34226","districtId":"2794","name":"Dororejo"},{"id":"34336","districtId":"2794","name":"Jepat Kidul"},{"id":"34337","districtId":"2794","name":"Jepat Lor"},{"id":"34375","districtId":"2794","name":"Kalikalong"},{"id":"34430","districtId":"2794","name":"Keboromo"},{"id":"34438","districtId":"2794","name":"Kedungbang"},{"id":"34446","districtId":"2794","name":"Kedungsari"},{"id":"34543","districtId":"2794","name":"Luwang"},{"id":"34555","districtId":"2794","name":"Margomulyo"},{"id":"34661","districtId":"2794","name":"Pakis"},{"id":"34738","districtId":"2794","name":"Pondowan"},{"id":"34752","districtId":"2794","name":"Pundenrejo"},{"id":"34758","districtId":"2794","name":"Purwokerto"}]