[{"id":"31285","districtId":"2834","name":"Tugu Lor"},{"id":"31295","districtId":"2834","name":"Tuwang"},{"id":"31299","districtId":"2834","name":"Undaan Kidul"},{"id":"31301","districtId":"2834","name":"Undaan Lor"},{"id":"31327","districtId":"2834","name":"Wonoketingal"},{"id":"31328","districtId":"2834","name":"Wonorejo"},{"id":"34113","districtId":"2834","name":"Bandungrejo"},{"id":"34195","districtId":"2834","name":"Cangkring"},{"id":"34196","districtId":"2834","name":"Cangkringrembang"},{"id":"34325","districtId":"2834","name":"Jatirejo"},{"id":"34390","districtId":"2834","name":"Karanganyar"},{"id":"34450","districtId":"2834","name":"Kedungwaru Kidul"},{"id":"34451","districtId":"2834","name":"Kedungwaru Lor"},{"id":"34474","districtId":"2834","name":"Ketanjung"},{"id":"34490","districtId":"2834","name":"Kotakan"},{"id":"34618","districtId":"2834","name":"Ngaluran"},{"id":"34637","districtId":"2834","name":"Ngemplikwetan"}]