[{"id":"2324","districtId":"322","name":"Miroto"},{"id":"2625","districtId":"322","name":"Pandansari"},{"id":"2733","districtId":"322","name":"Pekunden"},{"id":"2818","districtId":"322","name":"Pindrikan Kidul"},{"id":"2819","districtId":"322","name":"Pindrikan Lor"},{"id":"4858","districtId":"322","name":"Bangunharjo"},{"id":"5132","districtId":"322","name":"Brumbungan"},{"id":"5446","districtId":"322","name":"Gabahan"},{"id":"5699","districtId":"322","name":"Jagalan"},{"id":"6058","districtId":"322","name":"Karang Kidul"},{"id":"6226","districtId":"322","name":"Kauman"},{"id":"6394","districtId":"322","name":"Kembangsari"},{"id":"6570","districtId":"322","name":"Kranggan"},{"id":"9200","districtId":"322","name":"Purwodinatan"},{"id":"9414","districtId":"322","name":"Sekayu"}]