[{"id":"39099","districtId":"3491","name":"Benteng"},{"id":"39411","districtId":"3491","name":"Giri Kusuma"},{"id":"40156","districtId":"3491","name":"Ladongi"},{"id":"40308","districtId":"3491","name":"Malangke"},{"id":"40592","districtId":"3491","name":"Pattimang"},{"id":"40616","districtId":"3491","name":"Pettelandung"},{"id":"40619","districtId":"3491","name":"Pince Pute"},{"id":"40663","districtId":"3491","name":"Pute Mata"},{"id":"40714","districtId":"3491","name":"Salekoe"},{"id":"40840","districtId":"3491","name":"Takkalala"},{"id":"40876","districtId":"3491","name":"Tandung"},{"id":"40940","districtId":"3491","name":"Tingkara"},{"id":"40958","districtId":"3491","name":"Tokke"},{"id":"40960","districtId":"3491","name":"Tolada"}]