[{"id":"2444","districtId":"397","name":"Ngampin"},{"id":"2645","districtId":"397","name":"Panjang"},{"id":"2674","districtId":"397","name":"Pasekan"},{"id":"4944","districtId":"397","name":"Baran"},{"id":"4982","districtId":"397","name":"Bejalen"},{"id":"6568","districtId":"397","name":"Kranggan"},{"id":"6616","districtId":"397","name":"Kupang"},{"id":"6729","districtId":"397","name":"Lodoyong"},{"id":"9092","districtId":"397","name":"Pojoksari"},{"id":"9806","districtId":"397","name":"Tambakboyo"}]