[{"id":"2487","districtId":"410","name":"Ngering"},{"id":"2581","districtId":"410","name":"Pakahan"},{"id":"2836","districtId":"410","name":"Plawikan"},{"id":"4808","districtId":"410","name":"Bakung"},{"id":"5395","districtId":"410","name":"Dompyongan"},{"id":"5595","districtId":"410","name":"Gondangan"},{"id":"5614","districtId":"410","name":"Granting"},{"id":"5841","districtId":"410","name":"Joton"},{"id":"6092","districtId":"410","name":"Karangdukuh"},{"id":"6550","districtId":"410","name":"Kraguman"},{"id":"9120","districtId":"410","name":"Prawatan"},{"id":"9279","districtId":"410","name":"Rejoso"},{"id":"9641","districtId":"410","name":"Somopuro"},{"id":"9757","districtId":"410","name":"Sumyang"},{"id":"9804","districtId":"410","name":"Tambakan"},{"id":"9842","districtId":"410","name":"Tangkisan Pos"},{"id":"9981","districtId":"410","name":"Titang"},{"id":"10198","districtId":"410","name":"Wonoboyo"}]