[{"id":"2523","districtId":"430","name":"Nyamat"},{"id":"2689","districtId":"430","name":"Patemon"},{"id":"4950","districtId":"430","name":"Barukan"},{"id":"5011","districtId":"430","name":"Bener"},{"id":"5184","districtId":"430","name":"Butuh"},{"id":"5319","districtId":"430","name":"Cukil"},{"id":"5439","districtId":"430","name":"Duren"},{"id":"6094","districtId":"430","name":"Karangduren"},{"id":"6519","districtId":"430","name":"Klero"},{"id":"9259","districtId":"430","name":"Regunung"},{"id":"9669","districtId":"430","name":"Sruwen"},{"id":"9685","districtId":"430","name":"Sugihan"},{"id":"9901","districtId":"430","name":"Tegalrejo"},{"id":"9917","districtId":"430","name":"Tegalwaton"},{"id":"9950","districtId":"430","name":"Tengaran"}]