[{"id":"2525","districtId":"432","name":"Nyatnyono"},{"id":"4833","districtId":"432","name":"Bandarjo"},{"id":"5116","districtId":"432","name":"Branjang"},{"id":"5214","districtId":"432","name":"Candirejo"},{"id":"5531","districtId":"432","name":"Genuk"},{"id":"5586","districtId":"432","name":"Gogik"},{"id":"6002","districtId":"432","name":"Kalisidi"},{"id":"6375","districtId":"432","name":"Keji"},{"id":"6668","districtId":"432","name":"Langensari"},{"id":"6714","districtId":"432","name":"Lerep"},{"id":"10097","districtId":"432","name":"Ungaran"}]