[{"id":"50","districtId":"45","name":"Cikalong"},{"id":"140","districtId":"45","name":"Cipaingeun"},{"id":"203","districtId":"45","name":"Cukangjayaguna"},{"id":"204","districtId":"45","name":"Cukangkawung"},{"id":"450","districtId":"45","name":"Leuwidulang"},{"id":"2887","districtId":"45","name":"Muncang"},{"id":"2946","districtId":"45","name":"Pakalongan"},{"id":"2995","districtId":"45","name":"Parumasan"},{"id":"3046","districtId":"45","name":"Raksajaya"},{"id":"3089","districtId":"45","name":"Sepatnunggal"},{"id":"3175","districtId":"45","name":"Sodonghilir"},{"id":"3181","districtId":"45","name":"Sukabakti"}]