[{"id":"2578","districtId":"453","name":"Paitan"},{"id":"4978","districtId":"453","name":"Bedono Karangduwur"},{"id":"4979","districtId":"453","name":"Bedono Kluwung"},{"id":"4980","districtId":"453","name":"Bedono Pageron"},{"id":"5382","districtId":"453","name":"Dilem"},{"id":"5495","districtId":"453","name":"Gedong"},{"id":"5535","districtId":"453","name":"Gesikan"},{"id":"5552","districtId":"453","name":"Girijoyo"},{"id":"5554","districtId":"453","name":"Girimulyo"},{"id":"5676","districtId":"453","name":"Gunungteges"},{"id":"5759","districtId":"453","name":"Jatiwangsan"},{"id":"5924","districtId":"453","name":"Kaliglagah"},{"id":"5962","districtId":"453","name":"Kalimeneng"},{"id":"6014","districtId":"453","name":"Kaliurip"},{"id":"6051","districtId":"453","name":"Kapiteran"},{"id":"6136","districtId":"453","name":"Karangluas"},{"id":"6329","districtId":"453","name":"Kedunglo"},{"id":"6339","districtId":"453","name":"Kedungpomahankulon"},{"id":"6340","districtId":"453","name":"Kedungpomahanwetan"},{"id":"6409","districtId":"453","name":"Kemiri Kidul"},{"id":"6411","districtId":"453","name":"Kemirilor"},{"id":"6452","districtId":"453","name":"Kerep"},{"id":"6592","districtId":"453","name":"Kroyokulon"},{"id":"6593","districtId":"453","name":"Kroyolor"},{"id":"6735","districtId":"453","name":"Loning"},{"id":"9179","districtId":"453","name":"Purbayan"},{"id":"9256","districtId":"453","name":"Rebug"},{"id":"9267","districtId":"453","name":"Rejosari"},{"id":"9280","districtId":"453","name":"Rejowinangun"},{"id":"9306","districtId":"453","name":"Rowobayem"},{"id":"9366","districtId":"453","name":"Samping"},{"id":"9507","districtId":"453","name":"Sidodadi"},{"id":"9692","districtId":"453","name":"Sukogelap"},{"id":"9781","districtId":"453","name":"Sutoragan"},{"id":"10087","districtId":"453","name":"Turus"},{"id":"10107","districtId":"453","name":"Waled"},{"id":"10134","districtId":"453","name":"Wanurojo"},{"id":"10179","districtId":"453","name":"Winong"},{"id":"10230","districtId":"453","name":"Wonosari"},{"id":"10243","districtId":"453","name":"Wonosuko"}]