[{"id":"2647","districtId":"477","name":"Panjangsari"},{"id":"2691","districtId":"477","name":"Patemon"},{"id":"4893","districtId":"477","name":"Banjarsari"},{"id":"5589","districtId":"477","name":"Gombong"},{"id":"6010","districtId":"477","name":"Kalitengah"},{"id":"6343","districtId":"477","name":"Kedungpuji"},{"id":"6422","districtId":"477","name":"Kemukus"},{"id":"6528","districtId":"477","name":"Klopogodo"},{"id":"9439","districtId":"477","name":"Semanding"},{"id":"9453","districtId":"477","name":"Semondo"},{"id":"9501","districtId":"477","name":"Sidayu"},{"id":"10161","districtId":"477","name":"Wero"},{"id":"10213","districtId":"477","name":"Wonokriyo"},{"id":"10241","districtId":"477","name":"Wonosigro"}]