[{"id":"51930","districtId":"4874","name":"Ampang Tareh Lumpo"},{"id":"51935","districtId":"4874","name":"Ampuan Lumpo"},{"id":"52007","districtId":"4874","name":"Balai Sinayan Lumpo"},{"id":"52132","districtId":"4874","name":"Batu Kunik Lumpo"},{"id":"52236","districtId":"4874","name":"Bukik Kaciak Lumpo"},{"id":"52289","districtId":"4874","name":"Bunga Pasang Salido"},{"id":"52446","districtId":"4874","name":"Gunung Bungkuak Lumpo"},{"id":"52817","districtId":"4874","name":"Koto Rawang"},{"id":"52985","districtId":"4874","name":"Limau Gadang Lumpo"},{"id":"53084","districtId":"4874","name":"Lumpo"},{"id":"53320","districtId":"4874","name":"Painan"},{"id":"53321","districtId":"4874","name":"Painan Selatan Painan"},{"id":"53322","districtId":"4874","name":"Painan Timur Painan"},{"id":"53788","districtId":"4874","name":"Sago Salido"},{"id":"53804","districtId":"4874","name":"Salido"},{"id":"53805","districtId":"4874","name":"Salido Sari Bulan"},{"id":"54198","districtId":"4874","name":"Sungai Gayo Lumpo"},{"id":"54262","districtId":"4874","name":"Sungai Sariak Lumpo"},{"id":"54409","districtId":"4874","name":"Tambang"},{"id":"54569","districtId":"4874","name":"Taratak Tangah Lumpo"}]