[{"id":"73646","districtId":"6861","name":"Cipondoh"},{"id":"73647","districtId":"6861","name":"Cipondoh Makmur"},{"id":"73648","districtId":"6861","name":"Cipondoh Indah"},{"id":"73649","districtId":"6861","name":"Gondrong"},{"id":"73650","districtId":"6861","name":"Kenanga"},{"id":"73651","districtId":"6861","name":"Petir"},{"id":"73652","districtId":"6861","name":"Ketapang"},{"id":"73653","districtId":"6861","name":"Poris Plawad"},{"id":"73654","districtId":"6861","name":"Poris Plawad Utara"},{"id":"73655","districtId":"6861","name":"Poris Plawad Indah"}]