[{"id":"7534","districtId":"897","name":"Badurame"},{"id":"7623","districtId":"897","name":"Balun"},{"id":"7630","districtId":"897","name":"Bambang"},{"id":"8868","districtId":"897","name":"Gedungboyountung"},{"id":"8874","districtId":"897","name":"Geger"},{"id":"12154","districtId":"897","name":"Karangwedoro"},{"id":"12242","districtId":"897","name":"Keben"},{"id":"12520","districtId":"897","name":"Kemlagigede"},{"id":"12521","districtId":"897","name":"Kemlagilor"},{"id":"12602","districtId":"897","name":"Kepudibener"},{"id":"13857","districtId":"897","name":"Ngujungrejo"},{"id":"14589","districtId":"897","name":"Pomahanjanggan"},{"id":"14791","districtId":"897","name":"Putatkumpul"},{"id":"17281","districtId":"897","name":"Sukoanyar"},{"id":"17364","districtId":"897","name":"Sukorejo"},{"id":"17803","districtId":"897","name":"Tambakploso"},{"id":"17971","districtId":"897","name":"Tawangrejo"},{"id":"18314","districtId":"897","name":"Turi"},{"id":"18362","districtId":"897","name":"Wangunrejo"}]