[{"id":"293","cityId":"34","name":"Ngombol"},{"id":"323","cityId":"34","name":"Gebang"},{"id":"343","cityId":"34","name":"Purworejo"},{"id":"351","cityId":"34","name":"Loano"},{"id":"369","cityId":"34","name":"Grabag"},{"id":"374","cityId":"34","name":"Purwodadi"},{"id":"388","cityId":"34","name":"Kaligesing"},{"id":"395","cityId":"34","name":"Pituruh"},{"id":"402","cityId":"34","name":"Bener"},{"id":"439","cityId":"34","name":"Kutoarjo"},{"id":"453","cityId":"34","name":"Kemiri"},{"id":"458","cityId":"34","name":"Bruno"},{"id":"459","cityId":"34","name":"Banyuurip"},{"id":"473","cityId":"34","name":"Butuh"},{"id":"497","cityId":"34","name":"Bayan"},{"id":"514","cityId":"34","name":"Bagelen"}]